purrfc/LICENSE
purrfc/README.md
purrfc/__init__.py
purrfc/requirements.txt
purrfc/session.py
purrfc-0.0.3.dist-info/METADATA
purrfc-0.0.3.dist-info/WHEEL
purrfc-0.0.3.dist-info/top_level.txt
purrfc-0.0.3.dist-info/RECORD
